cleands/__init__.py
cleands/base.py
cleands/formula.py
cleands/utils.py
cleands/Classification/__init__.py
cleands/Classification/ensemble.py
cleands/Classification/glm.py
cleands/Classification/knn.py
cleands/Classification/lda.py
cleands/Classification/nb.py
cleands/Classification/tree.py
cleands/Clustering/__init__.py
cleands/Clustering/kmeans.py
cleands/DimensionReduction/__init__.py
cleands/DimensionReduction/pca.py
cleands/Distribution/__init__.py
cleands/Distribution/dist.py
cleands/Prediction/__init__.py
cleands/Prediction/ensemble.py
cleands/Prediction/glm.py
cleands/Prediction/knn.py
cleands/Prediction/ldv.py
cleands/Prediction/shrinkage.py
cleands/Prediction/tree.py
cleands-0.2.0.dist-info/licenses/LICENSE
cleands-0.2.0.dist-info/METADATA
cleands-0.2.0.dist-info/WHEEL
cleands-0.2.0.dist-info/top_level.txt
cleands-0.2.0.dist-info/RECORD
